wifiPassword/__init__.py
wifiPassword/wifiPassword.py
wifiPassword-2.0.dist-info/LICENSE.txt
wifiPassword-2.0.dist-info/METADATA
wifiPassword-2.0.dist-info/WHEEL
wifiPassword-2.0.dist-info/entry_points.txt
wifiPassword-2.0.dist-info/top_level.txt
wifiPassword-2.0.dist-info/RECORD
