Metadata-Version: 2.1
Name: wifiPassword
Version: 2.0
Summary: A cross platform CLI tool to get connected wifi network's password.
Home-page: https://github.com/ankitjain28may/wifiPassword
Author: Ankit Jain
Author-email: ankitjain28may77@gmail.com
License: MIT
Keywords: cli utility,cli-tool,cross-platform,wifiPassword,wifi,password,wifi password ubuntu,wifi password windows
Platform: UNKNOWN
Classifier: Development Status :: 4 - Beta
Classifier: Environment :: Console
Classifier: Intended Audience :: Developers
Classifier: Intended Audience :: Information Technology
Classifier: Natural Language :: English
Classifier: Topic :: Software Development :: Build Tools
Classifier: License :: OSI Approved :: MIT License
Classifier: Programming Language :: Python :: 2
Classifier: Programming Language :: Python :: 2.7
Classifier: Programming Language :: Python :: 3
Classifier: Programming Language :: Python :: 3.4
Classifier: Programming Language :: Python :: 3.5
Classifier: Programming Language :: Python :: 3.7
Requires-Dist: colorama (>=0.3.7)
